{
  "datasets": [
    {
      "type": "dataset",
      "title": "Policies",
      "id": "dataset.csv_policies",
      "columns": [
        {
          "type": "anchor",
          "id": "attr.csv_policies.factsof",
          "title": "Records of Policies",
          "description": null,
          "folder": null
        },
        {
          "type": "attribute",
          "id": "attr.csv_policies.customer",
          "title": "Customer",
          "description": null,
          "folder": "Policies"
        },
        {
          "type": "label",
          "id": "label.csv_policies.customer",
          "reference": "attr.csv_policies.customer",
          "title": "Customer",
          "gd_data_type": "VARCHAR(255)",
          "gd_type": "GDC.text",
          "default_label": true
        },
        {
          "type": "attribute",
          "id": "attr.csv_policies.state",
          "title": "State",
          "description": null,
          "folder": "Policies"
        },
        {
          "type": "label",
          "id": "label.csv_policies.state",
          "reference": "attr.csv_policies.state",
          "title": "State",
          "gd_data_type": "VARCHAR(255)",
          "gd_type": "GDC.text",
          "default_label": true
        },
        {
          "type": "attribute",
          "id": "attr.csv_policies.coverage",
          "title": "Coverage",
          "description": null,
          "folder": "Policies"
        },
        {
          "type": "label",
          "id": "label.csv_policies.coverage",
          "reference": "attr.csv_policies.coverage",
          "title": "Coverage",
          "gd_data_type": "VARCHAR(255)",
          "gd_type": "GDC.text",
          "default_label": true
        },
        {
          "type": "attribute",
          "id": "attr.csv_policies.education",
          "title": "Education",
          "description": null,
          "folder": "Policies"
        },
        {
          "type": "label",
          "id": "label.csv_policies.education",
          "reference": "attr.csv_policies.education",
          "title": "Education",
          "gd_data_type": "VARCHAR(255)",
          "gd_type": "GDC.text",
          "default_label": true
        },
        {
          "type": "attribute",
          "id": "attr.csv_policies.employmentstatus",
          "title": "Employmentstatus",
          "description": null,
          "folder": "Policies"
        },
        {
          "type": "label",
          "id": "label.csv_policies.employmentstatus",
          "reference": "attr.csv_policies.employmentstatus",
          "title": "Employmentstatus",
          "gd_data_type": "VARCHAR(255)",
          "gd_type": "GDC.text",
          "default_label": true
        },
        {
          "type": "attribute",
          "id": "attr.csv_policies.gender",
          "title": "Gender",
          "description": null,
          "folder": "Policies"
        },
        {
          "type": "label",
          "id": "label.csv_policies.gender",
          "reference": "attr.csv_policies.gender",
          "title": "Gender",
          "gd_data_type": "VARCHAR(255)",
          "gd_type": "GDC.text",
          "default_label": true
        },
        {
          "type": "attribute",
          "id": "attr.csv_policies.marital_status",
          "title": "Marital Status",
          "description": null,
          "folder": "Policies"
        },
        {
          "type": "label",
          "id": "label.csv_policies.marital_status",
          "reference": "attr.csv_policies.marital_status",
          "title": "Marital Status",
          "gd_data_type": "VARCHAR(255)",
          "gd_type": "GDC.text",
          "default_label": true
        },
        {
          "type": "attribute",
          "id": "attr.csv_policies.policy_type",
          "title": "Policy Type",
          "description": null,
          "folder": "Policies"
        },
        {
          "type": "label",
          "id": "label.csv_policies.policy_type",
          "reference": "attr.csv_policies.policy_type",
          "title": "Policy Type",
          "gd_data_type": "VARCHAR(255)",
          "gd_type": "GDC.text",
          "default_label": true
        },
        {
          "type": "attribute",
          "id": "attr.csv_policies.renew_offer_type",
          "title": "Renew Offer Type",
          "description": null,
          "folder": "Policies"
        },
        {
          "type": "label",
          "id": "label.csv_policies.renew_offer_type",
          "reference": "attr.csv_policies.renew_offer_type",
          "title": "Renew Offer Type",
          "gd_data_type": "VARCHAR(255)",
          "gd_type": "GDC.text",
          "default_label": true
        },
        {
          "type": "attribute",
          "id": "attr.csv_policies.sales_channel",
          "title": "Sales Channel",
          "description": null,
          "folder": "Policies"
        },
        {
          "type": "label",
          "id": "label.csv_policies.sales_channel",
          "reference": "attr.csv_policies.sales_channel",
          "title": "Sales Channel",
          "gd_data_type": "VARCHAR(255)",
          "gd_type": "GDC.text",
          "default_label": true
        },
        {
          "type": "attribute",
          "id": "attr.csv_policies.vehicle_class",
          "title": "Vehicle Class",
          "description": null,
          "folder": "Policies"
        },
        {
          "type": "label",
          "id": "label.csv_policies.vehicle_class",
          "reference": "attr.csv_policies.vehicle_class",
          "title": "Vehicle Class",
          "gd_data_type": "VARCHAR(255)",
          "gd_type": "GDC.text",
          "default_label": true
        },
        {
          "type": "attribute",
          "id": "attr.csv_policies.vehicle_size",
          "title": "Vehicle Size",
          "description": null,
          "folder": "Policies"
        },
        {
          "type": "label",
          "id": "label.csv_policies.vehicle_size",
          "reference": "attr.csv_policies.vehicle_size",
          "title": "Vehicle Size",
          "gd_data_type": "VARCHAR(255)",
          "gd_type": "GDC.text",
          "default_label": true
        },
        {
          "type": "fact",
          "id": "fact.csv_policies.customer_lifetime_value",
          "title": "Customer Lifetime Value",
          "folder": "Policies",
          "gd_data_type": "DECIMAL(15,6)",
          "restricted": true
        },
        {
          "type": "fact",
          "id": "fact.csv_policies.income",
          "title": "Income",
          "folder": "Policies",
          "gd_data_type": "DECIMAL(15,6)",
          "restricted": true
        },
        {
          "type": "fact",
          "id": "fact.csv_policies.monthly_premium_auto",
          "title": "Monthly Premium Auto",
          "folder": "Policies",
          "gd_data_type": "DECIMAL(15,6)"
        },
        {
          "type": "fact",
          "id": "fact.csv_policies.total_claim_amount",
          "title": "Total Claim Amount",
          "folder": "Policies",
          "gd_data_type": "DECIMAL(15,6)"
        },
        {
          "type": "date",
          "dataset": "effective_to_date"
        }
      ]
    }
  ],
  "date_dimensions": [
    {
      "type": "date_dimension",
      "id": "effective_to_date",
      "title": "Effective To Date"
    }
  ],
  "title": "QA Infra"
}